python/potato.py
potato.py-1.0.0.dist-info/LICENSE
potato.py-1.0.0.dist-info/METADATA
potato.py-1.0.0.dist-info/WHEEL
potato.py-1.0.0.dist-info/top_level.txt
potato.py-1.0.0.dist-info/RECORD
